{
	"__comment": "Designed by NyaaCat with Cubik Studio - https://cubik.studio",
	"gui_light": "front",
	"textures": {
		"p2020": "custom/p2020"
	},
	"elements": [ 	 
		{
			"__comment": "Voxels-440000",
			"from": [ 1.5, 3.5, 8 ],
			"to": [ 4, 4, 8.5 ],
			"faces": {
				"down": { "uv": [ 8.96, 0.96, 11.04, 3.04 ], "texture": "#p2020" },
				"up": { "uv": [ 8.96, 0.96, 11.04, 3.04 ], "texture": "#p2020" },
				"north": { "uv": [ 8.96, 0.96, 11.04, 3.04 ], "texture": "#p2020" },
				"south": { "uv": [ 8.96, 0.96, 11.04, 3.04 ], "texture": "#p2020" },
				"west": { "uv": [ 8.96, 0.96, 11.04, 3.04 ], "texture": "#p2020" },
				"east": { "uv": [ 8.96, 0.96, 11.04, 3.04 ], "texture": "#p2020" }
			}
		},
		{
			"__comment": "Voxels-440000",
			"from": [ 1.5, 4, 8 ],
			"to": [ 2, 7, 8.5 ],
			"faces": {
				"up": { "uv": [ 8.96, 0.96, 11.04, 3.04 ], "texture": "#p2020" },
				"north": { "uv": [ 8.96, 0.96, 11.04, 3.04 ], "texture": "#p2020" },
				"south": { "uv": [ 8.96, 0.96, 11.04, 3.04 ], "texture": "#p2020" },
				"west": { "uv": [ 8.96, 0.96, 11.04, 3.04 ], "texture": "#p2020" }
			}
		},
		{
			"__comment": "Voxels-111111",
			"from": [ 1.5, 4.5, 7.5 ],
			"to": [ 2.5, 6.5, 8 ],
			"faces": {
				"down": { "uv": [ 4.96, 4.96, 7.04, 7.04 ], "texture": "#p2020" },
				"up": { "uv": [ 4.96, 4.96, 7.04, 7.04 ], "texture": "#p2020" },
				"north": { "uv": [ 4.96, 4.96, 7.04, 7.04 ], "texture": "#p2020" },
				"south": { "uv": [ 4.96, 4.96, 7.04, 7.04 ], "texture": "#p2020" },
				"west": { "uv": [ 4.96, 4.96, 7.04, 7.04 ], "texture": "#p2020" }
			}
		},
		{
			"__comment": "Voxels-111111",
			"from": [ 1.5, 4.5, 8.5 ],
			"to": [ 2.5, 6.5, 9 ],
			"faces": {
				"down": { "uv": [ 4.96, 4.96, 7.04, 7.04 ], "texture": "#p2020" },
				"up": { "uv": [ 4.96, 4.96, 7.04, 7.04 ], "texture": "#p2020" },
				"north": { "uv": [ 4.96, 4.96, 7.04, 7.04 ], "texture": "#p2020" },
				"south": { "uv": [ 4.96, 4.96, 7.04, 7.04 ], "texture": "#p2020" },
				"west": { "uv": [ 4.96, 4.96, 7.04, 7.04 ], "texture": "#p2020" }
			}
		},
		{
			"__comment": "Voxels-111111",
			"from": [ 1.5, 9.5, 7.5 ],
			"to": [ 3, 10, 8.5 ],
			"faces": {
				"down": { "uv": [ 4.96, 4.96, 7.04, 7.04 ], "texture": "#p2020" },
				"up": { "uv": [ 4.96, 4.96, 7.04, 7.04 ], "texture": "#p2020" },
				"north": { "uv": [ 4.96, 4.96, 7.04, 7.04 ], "texture": "#p2020" },
				"south": { "uv": [ 4.96, 4.96, 7.04, 7.04 ], "texture": "#p2020" },
				"west": { "uv": [ 4.96, 4.96, 7.04, 7.04 ], "texture": "#p2020" },
				"east": { "uv": [ 4.96, 4.96, 7.04, 7.04 ], "texture": "#p2020" }
			}
		},
		{
			"__comment": "Voxels-111111",
			"from": [ 1.5, 9.5, 8.5 ],
			"to": [ 2.5, 10, 9 ],
			"faces": {
				"down": { "uv": [ 4.96, 4.96, 7.04, 7.04 ], "texture": "#p2020" },
				"up": { "uv": [ 4.96, 4.96, 7.04, 7.04 ], "texture": "#p2020" },
				"south": { "uv": [ 4.96, 4.96, 7.04, 7.04 ], "texture": "#p2020" },
				"west": { "uv": [ 4.96, 4.96, 7.04, 7.04 ], "texture": "#p2020" }
			}
		},
		{
			"__comment": "Voxels-440000",
			"from": [ 1.5, 10, 7.5 ],
			"to": [ 3, 10.5, 8 ],
			"faces": {
				"up": { "uv": [ 8.96, 0.96, 11.04, 3.04 ], "texture": "#p2020" },
				"north": { "uv": [ 8.96, 0.96, 11.04, 3.04 ], "texture": "#p2020" },
				"south": { "uv": [ 8.96, 0.96, 11.04, 3.04 ], "texture": "#p2020" },
				"west": { "uv": [ 8.96, 0.96, 11.04, 3.04 ], "texture": "#p2020" }
			}
		},
		{
			"__comment": "Voxels-440000",
			"from": [ 1.5, 10, 8 ],
			"to": [ 2, 10.5, 9 ],
			"faces": {
				"down": { "uv": [ 8.96, 0.96, 11.04, 3.04 ], "texture": "#p2020" },
				"up": { "uv": [ 8.96, 0.96, 11.04, 3.04 ], "texture": "#p2020" },
				"south": { "uv": [ 8.96, 0.96, 11.04, 3.04 ], "texture": "#p2020" },
				"west": { "uv": [ 8.96, 0.96, 11.04, 3.04 ], "texture": "#p2020" },
				"east": { "uv": [ 8.96, 0.96, 11.04, 3.04 ], "texture": "#p2020" }
			}
		},
		{
			"__comment": "Voxels-440000",
			"from": [ 2, 3, 7 ],
			"to": [ 4, 3.5, 8 ],
			"faces": {
				"down": { "uv": [ 8.96, 0.96, 11.04, 3.04 ], "texture": "#p2020" },
				"up": { "uv": [ 8.96, 0.96, 11.04, 3.04 ], "texture": "#p2020" },
				"north": { "uv": [ 8.96, 0.96, 11.04, 3.04 ], "texture": "#p2020" },
				"south": { "uv": [ 8.96, 0.96, 11.04, 3.04 ], "texture": "#p2020" },
				"west": { "uv": [ 8.96, 0.96, 11.04, 3.04 ], "texture": "#p2020" },
				"east": { "uv": [ 8.96, 0.96, 11.04, 3.04 ], "texture": "#p2020" }
			}
		},
		{
			"__comment": "Voxels-440000",
			"from": [ 2, 3, 8 ],
			"to": [ 3.5, 3.5, 9.5 ],
			"faces": {
				"down": { "uv": [ 8.96, 0.96, 11.04, 3.04 ], "texture": "#p2020" },
				"up": { "uv": [ 8.96, 0.96, 11.04, 3.04 ], "texture": "#p2020" },
				"south": { "uv": [ 8.96, 0.96, 11.04, 3.04 ], "texture": "#p2020" },
				"west": { "uv": [ 8.96, 0.96, 11.04, 3.04 ], "texture": "#p2020" },
				"east": { "uv": [ 8.96, 0.96, 11.04, 3.04 ], "texture": "#p2020" }
			}
		},
		{
			"__comment": "Voxels-440000",
			"from": [ 2, 3.5, 7.5 ],
			"to": [ 4, 4, 8 ],
			"faces": {
				"north": { "uv": [ 8.96, 0.96, 11.04, 3.04 ], "texture": "#p2020" },
				"west": { "uv": [ 8.96, 0.96, 11.04, 3.04 ], "texture": "#p2020" },
				"east": { "uv": [ 8.96, 0.96, 11.04, 3.04 ], "texture": "#p2020" }
			}
		},
		{
			"__comment": "Voxels-440000",
			"from": [ 2, 3.5, 8.5 ],
			"to": [ 4, 4, 9 ],
			"faces": {
				"down": { "uv": [ 8.96, 0.96, 11.04, 3.04 ], "texture": "#p2020" },
				"south": { "uv": [ 8.96, 0.96, 11.04, 3.04 ], "texture": "#p2020" },
				"west": { "uv": [ 8.96, 0.96, 11.04, 3.04 ], "texture": "#p2020" },
				"east": { "uv": [ 8.96, 0.96, 11.04, 3.04 ], "texture": "#p2020" }
			}
		},
		{
			"__comment": "Voxels-111111",
			"from": [ 2, 4, 7.5 ],
			"to": [ 4, 4.5, 8 ],
			"faces": {
				"up": { "uv": [ 4.96, 4.96, 7.04, 7.04 ], "texture": "#p2020" },
				"north": { "uv": [ 4.96, 4.96, 7.04, 7.04 ], "texture": "#p2020" },
				"south": { "uv": [ 4.96, 4.96, 7.04, 7.04 ], "texture": "#p2020" },
				"west": { "uv": [ 4.96, 4.96, 7.04, 7.04 ], "texture": "#p2020" },
				"east": { "uv": [ 4.96, 4.96, 7.04, 7.04 ], "texture": "#p2020" }
			}
		},
		{
			"__comment": "Voxels-DDDDDD",
			"from": [ 2, 4, 8 ],
			"to": [ 3.5, 7, 8.5 ],
			"faces": {
				"up": { "uv": [ 12.96, 4.96, 15.04, 7.04 ], "texture": "#p2020" },
				"north": { "uv": [ 12.96, 4.96, 15.04, 7.04 ], "texture": "#p2020" },
				"south": { "uv": [ 12.96, 4.96, 15.04, 7.04 ], "texture": "#p2020" },
				"east": { "uv": [ 12.96, 4.96, 15.04, 7.04 ], "texture": "#p2020" }
			}
		},
		{
			"__comment": "Voxels-111111",
			"from": [ 2, 4, 8.5 ],
			"to": [ 4, 4.5, 9 ],
			"faces": {
				"up": { "uv": [ 4.96, 4.96, 7.04, 7.04 ], "texture": "#p2020" },
				"north": { "uv": [ 4.96, 4.96, 7.04, 7.04 ], "texture": "#p2020" },
				"south": { "uv": [ 4.96, 4.96, 7.04, 7.04 ], "texture": "#p2020" },
				"west": { "uv": [ 4.96, 4.96, 7.04, 7.04 ], "texture": "#p2020" },
				"east": { "uv": [ 4.96, 4.96, 7.04, 7.04 ], "texture": "#p2020" }
			}
		},
		{
			"__comment": "Voxels-111111",
			"from": [ 2, 6.5, 7.5 ],
			"to": [ 3, 7, 8 ],
			"faces": {
				"down": { "uv": [ 4.96, 4.96, 7.04, 7.04 ], "texture": "#p2020" },
				"up": { "uv": [ 4.96, 4.96, 7.04, 7.04 ], "texture": "#p2020" },
				"north": { "uv": [ 4.96, 4.96, 7.04, 7.04 ], "texture": "#p2020" },
				"west": { "uv": [ 4.96, 4.96, 7.04, 7.04 ], "texture": "#p2020" }
			}
		},
		{
			"__comment": "Voxels-111111",
			"from": [ 2, 6.5, 8.5 ],
			"to": [ 3, 7, 9 ],
			"faces": {
				"down": { "uv": [ 4.96, 4.96, 7.04, 7.04 ], "texture": "#p2020" },
				"up": { "uv": [ 4.96, 4.96, 7.04, 7.04 ], "texture": "#p2020" },
				"south": { "uv": [ 4.96, 4.96, 7.04, 7.04 ], "texture": "#p2020" },
				"west": { "uv": [ 4.96, 4.96, 7.04, 7.04 ], "texture": "#p2020" }
			}
		},
		{
			"__comment": "Voxels-440000",
			"from": [ 2, 7, 8 ],
			"to": [ 2.5, 7.5, 8.5 ],
			"faces": {
				"up": { "uv": [ 8.96, 0.96, 11.04, 3.04 ], "texture": "#p2020" },
				"north": { "uv": [ 8.96, 0.96, 11.04, 3.04 ], "texture": "#p2020" },
				"south": { "uv": [ 8.96, 0.96, 11.04, 3.04 ], "texture": "#p2020" },
				"west": { "uv": [ 8.96, 0.96, 11.04, 3.04 ], "texture": "#p2020" }
			}
		},
		{
			"__comment": "Voxels-111111",
			"from": [ 2, 9, 8 ],
			"to": [ 2.5, 9.5, 8.5 ],
			"faces": {
				"down": { "uv": [ 4.96, 4.96, 7.04, 7.04 ], "texture": "#p2020" },
				"north": { "uv": [ 4.96, 4.96, 7.04, 7.04 ], "texture": "#p2020" },
				"south": { "uv": [ 4.96, 4.96, 7.04, 7.04 ], "texture": "#p2020" },
				"west": { "uv": [ 4.96, 4.96, 7.04, 7.04 ], "texture": "#p2020" }
			}
		},
		{
			"__comment": "Voxels-DDDDDD",
			"from": [ 2, 10, 8 ],
			"to": [ 8.5, 10.5, 8.5 ],
			"faces": {
				"down": { "uv": [ 12.96, 4.96, 15.04, 7.04 ], "texture": "#p2020" },
				"up": { "uv": [ 12.96, 4.96, 15.04, 7.04 ], "texture": "#p2020" },
				"north": { "uv": [ 12.96, 4.96, 15.04, 7.04 ], "texture": "#p2020" },
				"south": { "uv": [ 12.96, 4.96, 15.04, 7.04 ], "texture": "#p2020" }
			}
		},
		{
			"__comment": "Voxels-440000",
			"from": [ 2, 10, 8.5 ],
			"to": [ 3, 10.5, 9 ],
			"faces": {
				"down": { "uv": [ 8.96, 0.96, 11.04, 3.04 ], "texture": "#p2020" },
				"south": { "uv": [ 8.96, 0.96, 11.04, 3.04 ], "texture": "#p2020" }
			}
		},
		{
			"__comment": "Voxels-220000",
			"from": [ 2, 10.5, 7.5 ],
			"to": [ 11.5, 11, 8 ],
			"faces": {
				"down": { "uv": [ 4.96, 0.96, 7.04, 3.04 ], "texture": "#p2020" },
				"up": { "uv": [ 4.96, 0.96, 7.04, 3.04 ], "texture": "#p2020" },
				"north": { "uv": [ 4.96, 0.96, 7.04, 3.04 ], "texture": "#p2020" },
				"south": { "uv": [ 4.96, 0.96, 7.04, 3.04 ], "texture": "#p2020" },
				"west": { "uv": [ 4.96, 0.96, 7.04, 3.04 ], "texture": "#p2020" }
			}
		},
		{
			"__comment": "Voxels-440000",
			"from": [ 2, 10.5, 8 ],
			"to": [ 2.5, 11, 8.5 ],
			"faces": {
				"up": { "uv": [ 8.96, 0.96, 11.04, 3.04 ], "texture": "#p2020" },
				"west": { "uv": [ 8.96, 0.96, 11.04, 3.04 ], "texture": "#p2020" }
			}
		},
		{
			"__comment": "Voxels-220000",
			"from": [ 2, 10.5, 8.5 ],
			"to": [ 11.5, 11, 9 ],
			"faces": {
				"down": { "uv": [ 4.96, 0.96, 7.04, 3.04 ], "texture": "#p2020" },
				"up": { "uv": [ 4.96, 0.96, 7.04, 3.04 ], "texture": "#p2020" },
				"north": { "uv": [ 4.96, 0.96, 7.04, 3.04 ], "texture": "#p2020" },
				"south": { "uv": [ 4.96, 0.96, 7.04, 3.04 ], "texture": "#p2020" },
				"west": { "uv": [ 4.96, 0.96, 7.04, 3.04 ], "texture": "#p2020" }
			}
		},
		{
			"__comment": "Voxels-220000",
			"from": [ 2.5, 4.5, 7.5 ],
			"to": [ 3, 6.5, 8 ],
			"faces": {
				"north": { "uv": [ 4.96, 0.96, 7.04, 3.04 ], "texture": "#p2020" },
				"east": { "uv": [ 4.96, 0.96, 7.04, 3.04 ], "texture": "#p2020" }
			}
		},
		{
			"__comment": "Voxels-220000",
			"from": [ 2.5, 4.5, 8.5 ],
			"to": [ 3, 6.5, 9 ],
			"faces": {
				"south": { "uv": [ 4.96, 0.96, 7.04, 3.04 ], "texture": "#p2020" },
				"east": { "uv": [ 4.96, 0.96, 7.04, 3.04 ], "texture": "#p2020" }
			}
		},
		{
			"__comment": "Voxels-111111",
			"from": [ 2.5, 7, 7.5 ],
			"to": [ 3.5, 7.5, 8 ],
			"faces": {
				"down": { "uv": [ 4.96, 4.96, 7.04, 7.04 ], "texture": "#p2020" },
				"up": { "uv": [ 4.96, 4.96, 7.04, 7.04 ], "texture": "#p2020" },
				"north": { "uv": [ 4.96, 4.96, 7.04, 7.04 ], "texture": "#p2020" },
				"west": { "uv": [ 4.96, 4.96, 7.04, 7.04 ], "texture": "#p2020" }
			}
		},
		{
			"__comment": "Voxels-DDDDDD",
			"from": [ 2.5, 7, 8 ],
			"to": [ 5, 7.5, 8.5 ],
			"faces": {
				"down": { "uv": [ 12.96, 4.96, 15.04, 7.04 ], "texture": "#p2020" },
				"up": { "uv": [ 12.96, 4.96, 15.04, 7.04 ], "texture": "#p2020" },
				"north": { "uv": [ 12.96, 4.96, 15.04, 7.04 ], "texture": "#p2020" },
				"south": { "uv": [ 12.96, 4.96, 15.04, 7.04 ], "texture": "#p2020" }
			}
		},
		{
			"__comment": "Voxels-111111",
			"from": [ 2.5, 7, 8.5 ],
			"to": [ 3.5, 7.5, 9 ],
			"faces": {
				"down": { "uv": [ 4.96, 4.96, 7.04, 7.04 ], "texture": "#p2020" },
				"up": { "uv": [ 4.96, 4.96, 7.04, 7.04 ], "texture": "#p2020" },
				"south": { "uv": [ 4.96, 4.96, 7.04, 7.04 ], "texture": "#p2020" },
				"west": { "uv": [ 4.96, 4.96, 7.04, 7.04 ], "texture": "#p2020" }
			}
		},
		{
			"__comment": "Voxels-440000",
			"from": [ 2.5, 7.5, 8 ],
			"to": [ 3, 8.5, 8.5 ],
			"faces": {
				"north": { "uv": [ 8.96, 0.96, 11.04, 3.04 ], "texture": "#p2020" },
				"south": { "uv": [ 8.96, 0.96, 11.04, 3.04 ], "texture": "#p2020" },
				"west": { "uv": [ 8.96, 0.96, 11.04, 3.04 ], "texture": "#p2020" }
			}
		},
		{
			"__comment": "Voxels-111111",
			"from": [ 2.5, 8.5, 8 ],
			"to": [ 5.5, 9, 8.5 ],
			"faces": {
				"down": { "uv": [ 4.96, 4.96, 7.04, 7.04 ], "texture": "#p2020" },
				"north": { "uv": [ 4.96, 4.96, 7.04, 7.04 ], "texture": "#p2020" },
				"south": { "uv": [ 4.96, 4.96, 7.04, 7.04 ], "texture": "#p2020" },
				"west": { "uv": [ 4.96, 4.96, 7.04, 7.04 ], "texture": "#p2020" }
			}
		},
		{
			"__comment": "Voxels-111111",
			"from": [ 2.5, 9, 7.5 ],
			"to": [ 3.5, 9.5, 8 ],
			"faces": {
				"down": { "uv": [ 4.96, 4.96, 7.04, 7.04 ], "texture": "#p2020" },
				"up": { "uv": [ 4.96, 4.96, 7.04, 7.04 ], "texture": "#p2020" },
				"north": { "uv": [ 4.96, 4.96, 7.04, 7.04 ], "texture": "#p2020" },
				"west": { "uv": [ 4.96, 4.96, 7.04, 7.04 ], "texture": "#p2020" }
			}
		},
		{
			"__comment": "Voxels-DDDDDD",
			"from": [ 2.5, 9, 8 ],
			"to": [ 5.5, 9.5, 8.5 ],
			"faces": {
				"up": { "uv": [ 12.96, 4.96, 15.04, 7.04 ], "texture": "#p2020" },
				"north": { "uv": [ 12.96, 4.96, 15.04, 7.04 ], "texture": "#p2020" },
				"south": { "uv": [ 12.96, 4.96, 15.04, 7.04 ], "texture": "#p2020" }
			}
		},
		{
			"__comment": "Voxels-111111",
			"from": [ 2.5, 9, 8.5 ],
			"to": [ 3.5, 9.5, 9 ],
			"faces": {
				"down": { "uv": [ 4.96, 4.96, 7.04, 7.04 ], "texture": "#p2020" },
				"south": { "uv": [ 4.96, 4.96, 7.04, 7.04 ], "texture": "#p2020" },
				"west": { "uv": [ 4.96, 4.96, 7.04, 7.04 ], "texture": "#p2020" }
			}
		},
		{
			"__comment": "Voxels-440000",
			"from": [ 2.5, 9.5, 8.5 ],
			"to": [ 6.5, 10, 9 ],
			"faces": {
				"down": { "uv": [ 8.96, 0.96, 11.04, 3.04 ], "texture": "#p2020" },
				"up": { "uv": [ 8.96, 0.96, 11.04, 3.04 ], "texture": "#p2020" },
				"north": { "uv": [ 8.96, 0.96, 11.04, 3.04 ], "texture": "#p2020" },
				"south": { "uv": [ 8.96, 0.96, 11.04, 3.04 ], "texture": "#p2020" }
			}
		},
		{
			"__comment": "Voxels-DDDDDD",
			"from": [ 2.5, 10.5, 8 ],
			"to": [ 13, 11, 8.5 ],
			"faces": {
				"down": { "uv": [ 12.96, 4.96, 15.04, 7.04 ], "texture": "#p2020" },
				"up": { "uv": [ 12.96, 4.96, 15.04, 7.04 ], "texture": "#p2020" },
				"north": { "uv": [ 12.96, 4.96, 15.04, 7.04 ], "texture": "#p2020" },
				"south": { "uv": [ 12.96, 4.96, 15.04, 7.04 ], "texture": "#p2020" }
			}
		},
		{
			"__comment": "Voxels-220000",
			"from": [ 2.5, 11, 7.5 ],
			"to": [ 3.5, 11.5, 8 ],
			"faces": {
				"up": { "uv": [ 4.96, 0.96, 7.04, 3.04 ], "texture": "#p2020" },
				"north": { "uv": [ 4.96, 0.96, 7.04, 3.04 ], "texture": "#p2020" },
				"south": { "uv": [ 4.96, 0.96, 7.04, 3.04 ], "texture": "#p2020" },
				"west": { "uv": [ 4.96, 0.96, 7.04, 3.04 ], "texture": "#p2020" }
			}
		},
		{
			"__comment": "Voxels-440000",
			"from": [ 2.5, 11, 8 ],
			"to": [ 3, 11.5, 8.5 ],
			"faces": {
				"up": { "uv": [ 8.96, 0.96, 11.04, 3.04 ], "texture": "#p2020" },
				"west": { "uv": [ 8.96, 0.96, 11.04, 3.04 ], "texture": "#p2020" }
			}
		},
		{
			"__comment": "Voxels-220000",
			"from": [ 2.5, 11, 8.5 ],
			"to": [ 3.5, 11.5, 9 ],
			"faces": {
				"up": { "uv": [ 4.96, 0.96, 7.04, 3.04 ], "texture": "#p2020" },
				"north": { "uv": [ 4.96, 0.96, 7.04, 3.04 ], "texture": "#p2020" },
				"south": { "uv": [ 4.96, 0.96, 7.04, 3.04 ], "texture": "#p2020" },
				"west": { "uv": [ 4.96, 0.96, 7.04, 3.04 ], "texture": "#p2020" }
			}
		},
		{
			"__comment": "Voxels-111111",
			"from": [ 3, 4.5, 7.5 ],
			"to": [ 4, 5.5, 8 ],
			"faces": {
				"up": { "uv": [ 4.96, 4.96, 7.04, 7.04 ], "texture": "#p2020" },
				"north": { "uv": [ 4.96, 4.96, 7.04, 7.04 ], "texture": "#p2020" },
				"south": { "uv": [ 4.96, 4.96, 7.04, 7.04 ], "texture": "#p2020" },
				"east": { "uv": [ 4.96, 4.96, 7.04, 7.04 ], "texture": "#p2020" }
			}
		},
		{
			"__comment": "Voxels-111111",
			"from": [ 3, 4.5, 8.5 ],
			"to": [ 4, 5.5, 9 ],
			"faces": {
				"up": { "uv": [ 4.96, 4.96, 7.04, 7.04 ], "texture": "#p2020" },
				"north": { "uv": [ 4.96, 4.96, 7.04, 7.04 ], "texture": "#p2020" },
				"south": { "uv": [ 4.96, 4.96, 7.04, 7.04 ], "texture": "#p2020" },
				"east": { "uv": [ 4.96, 4.96, 7.04, 7.04 ], "texture": "#p2020" }
			}
		},
		{
			"__comment": "Voxels-220000",
			"from": [ 3, 5.5, 7.5 ],
			"to": [ 3.5, 7, 8 ],
			"faces": {
				"north": { "uv": [ 4.96, 0.96, 7.04, 3.04 ], "texture": "#p2020" },
				"west": { "uv": [ 4.96, 0.96, 7.04, 3.04 ], "texture": "#p2020" },
				"east": { "uv": [ 4.96, 0.96, 7.04, 3.04 ], "texture": "#p2020" }
			}
		},
		{
			"__comment": "Voxels-220000",
			"from": [ 3, 5.5, 8.5 ],
			"to": [ 3.5, 7, 9 ],
			"faces": {
				"south": { "uv": [ 4.96, 0.96, 7.04, 3.04 ], "texture": "#p2020" },
				"west": { "uv": [ 4.96, 0.96, 7.04, 3.04 ], "texture": "#p2020" },
				"east": { "uv": [ 4.96, 0.96, 7.04, 3.04 ], "texture": "#p2020" }
			}
		},
		{
			"__comment": "Voxels-111111",
			"from": [ 3, 7.5, 7.5 ],
			"to": [ 3.5, 9, 8 ],
			"faces": {
				"north": { "uv": [ 4.96, 4.96, 7.04, 7.04 ], "texture": "#p2020" },
				"south": { "uv": [ 4.96, 4.96, 7.04, 7.04 ], "texture": "#p2020" },
				"west": { "uv": [ 4.96, 4.96, 7.04, 7.04 ], "texture": "#p2020" },
				"east": { "uv": [ 4.96, 4.96, 7.04, 7.04 ], "texture": "#p2020" }
			}
		},
		{
			"__comment": "Voxels-DDDDDD",
			"from": [ 3, 7.5, 8 ],
			"to": [ 5.5, 8.5, 8.5 ],
			"faces": {
				"down": { "uv": [ 12.96, 4.96, 15.04, 7.04 ], "texture": "#p2020" },
				"north": { "uv": [ 12.96, 4.96, 15.04, 7.04 ], "texture": "#p2020" },
				"south": { "uv": [ 12.96, 4.96, 15.04, 7.04 ], "texture": "#p2020" },
				"east": { "uv": [ 12.96, 4.96, 15.04, 7.04 ], "texture": "#p2020" }
			}
		},
		{
			"__comment": "Voxels-111111",
			"from": [ 3, 7.5, 8.5 ],
			"to": [ 3.5, 9, 9 ],
			"faces": {
				"north": { "uv": [ 4.96, 4.96, 7.04, 7.04 ], "texture": "#p2020" },
				"south": { "uv": [ 4.96, 4.96, 7.04, 7.04 ], "texture": "#p2020" },
				"west": { "uv": [ 4.96, 4.96, 7.04, 7.04 ], "texture": "#p2020" },
				"east": { "uv": [ 4.96, 4.96, 7.04, 7.04 ], "texture": "#p2020" }
			}
		},
		{
			"__comment": "Voxels-440000",
			"from": [ 3, 9.5, 7.5 ],
			"to": [ 6.5, 10, 8 ],
			"faces": {
				"down": { "uv": [ 8.96, 0.96, 11.04, 3.04 ], "texture": "#p2020" },
				"up": { "uv": [ 8.96, 0.96, 11.04, 3.04 ], "texture": "#p2020" },
				"north": { "uv": [ 8.96, 0.96, 11.04, 3.04 ], "texture": "#p2020" },
				"south": { "uv": [ 8.96, 0.96, 11.04, 3.04 ], "texture": "#p2020" }
			}
		},
		{
			"__comment": "Voxels-DDDDDD",
			"from": [ 3, 9.5, 8 ],
			"to": [ 6, 10, 8.5 ],
			"faces": {
				"down": { "uv": [ 12.96, 4.96, 15.04, 7.04 ], "texture": "#p2020" }
			}
		},
		{
			"__comment": "Voxels-444444",
			"from": [ 3, 10, 7.5 ],
			"to": [ 4, 10.5, 8 ],
			"faces": {
				"north": { "uv": [ 8.96, 8.96, 11.04, 11.04 ], "texture": "#p2020" }
			}
		},
		{
			"__comment": "Voxels-444444",
			"from": [ 3, 10, 8.5 ],
			"to": [ 4, 10.5, 9 ],
			"faces": {
				"south": { "uv": [ 8.96, 8.96, 11.04, 11.04 ], "texture": "#p2020" }
			}
		},
		{
			"__comment": "Voxels-DDDDDD",
			"from": [ 3, 11, 8 ],
			"to": [ 13, 11.5, 8.5 ],
			"faces": {
				"up": { "uv": [ 12.96, 4.96, 15.04, 7.04 ], "texture": "#p2020" },
				"north": { "uv": [ 12.96, 4.96, 15.04, 7.04 ], "texture": "#p2020" },
				"south": { "uv": [ 12.96, 4.96, 15.04, 7.04 ], "texture": "#p2020" }
			}
		},
		{
			"__comment": "Voxels-220000",
			"from": [ 3, 11.5, 8 ],
			"to": [ 4, 12, 8.5 ],
			"faces": {
				"up": { "uv": [ 4.96, 0.96, 7.04, 3.04 ], "texture": "#p2020" },
				"north": { "uv": [ 4.96, 0.96, 7.04, 3.04 ], "texture": "#p2020" },
				"south": { "uv": [ 4.96, 0.96, 7.04, 3.04 ], "texture": "#p2020" },
				"west": { "uv": [ 4.96, 0.96, 7.04, 3.04 ], "texture": "#p2020" }
			}
		},
		{
			"__comment": "Voxels-440000",
			"from": [ 3.5, 2.5, 7 ],
			"to": [ 5, 3, 9.5 ],
			"faces": {
				"down": { "uv": [ 8.96, 0.96, 11.04, 3.04 ], "texture": "#p2020" },
				"up": { "uv": [ 8.96, 0.96, 11.04, 3.04 ], "texture": "#p2020" },
				"north": { "uv": [ 8.96, 0.96, 11.04, 3.04 ], "texture": "#p2020" },
				"south": { "uv": [ 8.96, 0.96, 11.04, 3.04 ], "texture": "#p2020" },
				"west": { "uv": [ 8.96, 0.96, 11.04, 3.04 ], "texture": "#p2020" },
				"east": { "uv": [ 8.96, 0.96, 11.04, 3.04 ], "texture": "#p2020" }
			}
		},
		{
			"__comment": "Voxels-DDDDDD",
			"from": [ 3.5, 3, 8 ],
			"to": [ 4, 3.5, 9 ],
			"faces": {
				"up": { "uv": [ 12.96, 4.96, 15.04, 7.04 ], "texture": "#p2020" }
			}
		},
		{
			"__comment": "Voxels-440000",
			"from": [ 3.5, 3, 9 ],
			"to": [ 4, 3.5, 9.5 ],
			"faces": {
				"up": { "uv": [ 8.96, 0.96, 11.04, 3.04 ], "texture": "#p2020" },
				"south": { "uv": [ 8.96, 0.96, 11.04, 3.04 ], "texture": "#p2020" },
				"east": { "uv": [ 8.96, 0.96, 11.04, 3.04 ], "texture": "#p2020" }
			}
		},
		{
			"__comment": "Voxels-111111",
			"from": [ 3.5, 4, 8 ],
			"to": [ 4, 4.5, 8.5 ],
			"faces": {
				"east": { "uv": [ 4.96, 4.96, 7.04, 7.04 ], "texture": "#p2020" }
			}
		},
		{
			"__comment": "Voxels-DDDDDD",
			"from": [ 3.5, 4.5, 8 ],
			"to": [ 4, 7, 8.5 ],
			"faces": {
				"north": { "uv": [ 12.96, 4.96, 15.04, 7.04 ], "texture": "#p2020" },
				"south": { "uv": [ 12.96, 4.96, 15.04, 7.04 ], "texture": "#p2020" },
				"east": { "uv": [ 12.96, 4.96, 15.04, 7.04 ], "texture": "#p2020" }
			}
		},
		{
			"__comment": "Voxels-111111",
			"from": [ 3.5, 5.5, 7.5 ],
			"to": [ 4.5, 6, 8 ],
			"faces": {
				"down": { "uv": [ 4.96, 4.96, 7.04, 7.04 ], "texture": "#p2020" },
				"up": { "uv": [ 4.96, 4.96, 7.04, 7.04 ], "texture": "#p2020" },
				"north": { "uv": [ 4.96, 4.96, 7.04, 7.04 ], "texture": "#p2020" },
				"south": { "uv": [ 4.96, 4.96, 7.04, 7.04 ], "texture": "#p2020" },
				"east": { "uv": [ 4.96, 4.96, 7.04, 7.04 ], "texture": "#p2020" }
			}
		},
		{
			"__comment": "Voxels-111111",
			"from": [ 3.5, 5.5, 8.5 ],
			"to": [ 4.5, 6, 9 ],
			"faces": {
				"down": { "uv": [ 4.96, 4.96, 7.04, 7.04 ], "texture": "#p2020" },
				"up": { "uv": [ 4.96, 4.96, 7.04, 7.04 ], "texture": "#p2020" },
				"north": { "uv": [ 4.96, 4.96, 7.04, 7.04 ], "texture": "#p2020" },
				"south": { "uv": [ 4.96, 4.96, 7.04, 7.04 ], "texture": "#p2020" },
				"east": { "uv": [ 4.96, 4.96, 7.04, 7.04 ], "texture": "#p2020" }
			}
		},
		{
			"__comment": "Voxels-220000",
			"from": [ 3.5, 6, 7.5 ],
			"to": [ 4, 8, 8 ],
			"faces": {
				"north": { "uv": [ 4.96, 0.96, 7.04, 3.04 ], "texture": "#p2020" },
				"south": { "uv": [ 4.96, 0.96, 7.04, 3.04 ], "texture": "#p2020" },
				"west": { "uv": [ 4.96, 0.96, 7.04, 3.04 ], "texture": "#p2020" }
			}
		},
		{
			"__comment": "Voxels-220000",
			"from": [ 3.5, 6, 8.5 ],
			"to": [ 4, 8, 9 ],
			"faces": {
				"north": { "uv": [ 4.96, 0.96, 7.04, 3.04 ], "texture": "#p2020" },
				"south": { "uv": [ 4.96, 0.96, 7.04, 3.04 ], "texture": "#p2020" },
				"west": { "uv": [ 4.96, 0.96, 7.04, 3.04 ], "texture": "#p2020" }
			}
		},
		{
			"__comment": "Voxels-111111",
			"from": [ 3.5, 8, 7.5 ],
			"to": [ 5.5, 8.5, 8 ],
			"faces": {
				"down": { "uv": [ 4.96, 4.96, 7.04, 7.04 ], "texture": "#p2020" },
				"up": { "uv": [ 4.96, 4.96, 7.04, 7.04 ], "texture": "#p2020" },
				"north": { "uv": [ 4.96, 4.96, 7.04, 7.04 ], "texture": "#p2020" },
				"east": { "uv": [ 4.96, 4.96, 7.04, 7.04 ], "texture": "#p2020" }
			}
		},
		{
			"__comment": "Voxels-111111",
			"from": [ 3.5, 8, 8.5 ],
			"to": [ 5, 8.5, 9 ],
			"faces": {
				"down": { "uv": [ 4.96, 4.96, 7.04, 7.04 ], "texture": "#p2020" },
				"up": { "uv": [ 4.96, 4.96, 7.04, 7.04 ], "texture": "#p2020" },
				"south": { "uv": [ 4.96, 4.96, 7.04, 7.04 ], "texture": "#p2020" }
			}
		},
		{
			"__comment": "Voxels-000011",
			"from": [ 3.5, 8.5, 7.5 ],
			"to": [ 4, 9, 8 ],
			"faces": {
				"north": { "uv": [ 8.96, 4.96, 11.04, 7.04 ], "texture": "#p2020" }
			}
		},
		{
			"__comment": "Voxels-000011",
			"from": [ 3.5, 8.5, 8.5 ],
			"to": [ 4, 9, 9 ],
			"faces": {
				"south": { "uv": [ 8.96, 4.96, 11.04, 7.04 ], "texture": "#p2020" }
			}
		},
		{
			"__comment": "Voxels-440000",
			"from": [ 3.5, 9, 7.5 ],
			"to": [ 5, 9.5, 8 ],
			"faces": {
				"down": { "uv": [ 8.96, 0.96, 11.04, 3.04 ], "texture": "#p2020" },
				"north": { "uv": [ 8.96, 0.96, 11.04, 3.04 ], "texture": "#p2020" }
			}
		},
		{
			"__comment": "Voxels-440000",
			"from": [ 3.5, 9, 8.5 ],
			"to": [ 5, 9.5, 9 ],
			"faces": {
				"down": { "uv": [ 8.96, 0.96, 11.04, 3.04 ], "texture": "#p2020" },
				"south": { "uv": [ 8.96, 0.96, 11.04, 3.04 ], "texture": "#p2020" }
			}
		},
		{
			"__comment": "Voxels-000011",
			"from": [ 3.5, 11, 7.5 ],
			"to": [ 5, 11.5, 8 ],
			"faces": {
				"up": { "uv": [ 8.96, 4.96, 11.04, 7.04 ], "texture": "#p2020" },
				"north": { "uv": [ 8.96, 4.96, 11.04, 7.04 ], "texture": "#p2020" }
			}
		},
		{
			"__comment": "Voxels-000011",
			"from": [ 3.5, 11, 8.5 ],
			"to": [ 5, 11.5, 9 ],
			"faces": {
				"up": { "uv": [ 8.96, 4.96, 11.04, 7.04 ], "texture": "#p2020" },
				"south": { "uv": [ 8.96, 4.96, 11.04, 7.04 ], "texture": "#p2020" }
			}
		},
		{
			"__comment": "Voxels-440000",
			"from": [ 4, 3, 7.5 ],
			"to": [ 4.5, 3.5, 9 ],
			"faces": {
				"up": { "uv": [ 8.96, 0.96, 11.04, 3.04 ], "texture": "#p2020" },
				"north": { "uv": [ 8.96, 0.96, 11.04, 3.04 ], "texture": "#p2020" },
				"south": { "uv": [ 8.96, 0.96, 11.04, 3.04 ], "texture": "#p2020" },
				"west": { "uv": [ 8.96, 0.96, 11.04, 3.04 ], "texture": "#p2020" },
				"east": { "uv": [ 8.96, 0.96, 11.04, 3.04 ], "texture": "#p2020" }
			}
		},
		{
			"__comment": "Voxels-111111",
			"from": [ 4, 4.5, 8 ],
			"to": [ 4.5, 6, 8.5 ],
			"faces": {
				"down": { "uv": [ 4.96, 4.96, 7.04, 7.04 ], "texture": "#p2020" },
				"north": { "uv": [ 4.96, 4.96, 7.04, 7.04 ], "texture": "#p2020" },
				"south": { "uv": [ 4.96, 4.96, 7.04, 7.04 ], "texture": "#p2020" },
				"east": { "uv": [ 4.96, 4.96, 7.04, 7.04 ], "texture": "#p2020" }
			}
		},
		{
			"__comment": "Voxels-111111",
			"from": [ 4, 6, 7.5 ],
			"to": [ 4.5, 8, 8 ],
			"faces": {
				"north": { "uv": [ 4.96, 4.96, 7.04, 7.04 ], "texture": "#p2020" },
				"south": { "uv": [ 4.96, 4.96, 7.04, 7.04 ], "texture": "#p2020" },
				"east": { "uv": [ 4.96, 4.96, 7.04, 7.04 ], "texture": "#p2020" }
			}
		},
		{
			"__comment": "Voxels-111111",
			"from": [ 4, 6, 8.5 ],
			"to": [ 4.5, 8, 9 ],
			"faces": {
				"north": { "uv": [ 4.96, 4.96, 7.04, 7.04 ], "texture": "#p2020" },
				"south": { "uv": [ 4.96, 4.96, 7.04, 7.04 ], "texture": "#p2020" },
				"east": { "uv": [ 4.96, 4.96, 7.04, 7.04 ], "texture": "#p2020" }
			}
		},
		{
			"__comment": "Voxels-111111",
			"from": [ 4, 8.5, 7.5 ],
			"to": [ 5.5, 9, 8 ],
			"faces": {
				"up": { "uv": [ 4.96, 4.96, 7.04, 7.04 ], "texture": "#p2020" },
				"north": { "uv": [ 4.96, 4.96, 7.04, 7.04 ], "texture": "#p2020" },
				"east": { "uv": [ 4.96, 4.96, 7.04, 7.04 ], "texture": "#p2020" }
			}
		},
		{
			"__comment": "Voxels-111111",
			"from": [ 4, 8.5, 8.5 ],
			"to": [ 5, 9, 9 ],
			"faces": {
				"south": { "uv": [ 4.96, 4.96, 7.04, 7.04 ], "texture": "#p2020" }
			}
		},
		{
			"__comment": "Voxels-555555",
			"from": [ 4, 10, 7.5 ],
			"to": [ 4.5, 10.5, 8 ],
			"faces": {
				"north": { "uv": [ 12.96, 0.96, 15.04, 3.04 ], "texture": "#p2020" }
			}
		},
		{
			"__comment": "Voxels-555555",
			"from": [ 4, 10, 8.5 ],
			"to": [ 4.5, 10.5, 9 ],
			"faces": {
				"south": { "uv": [ 12.96, 0.96, 15.04, 3.04 ], "texture": "#p2020" }
			}
		},
		{
			"__comment": "Voxels-000011",
			"from": [ 4, 11.5, 8 ],
			"to": [ 5, 12, 8.5 ],
			"faces": {
				"up": { "uv": [ 8.96, 4.96, 11.04, 7.04 ], "texture": "#p2020" },
				"north": { "uv": [ 8.96, 4.96, 11.04, 7.04 ], "texture": "#p2020" },
				"south": { "uv": [ 8.96, 4.96, 11.04, 7.04 ], "texture": "#p2020" }
			}
		},
		{
			"__comment": "Voxels-111111",
			"from": [ 4.5, 6, 8 ],
			"to": [ 5, 7, 8.5 ],
			"faces": {
				"down": { "uv": [ 4.96, 4.96, 7.04, 7.04 ], "texture": "#p2020" },
				"north": { "uv": [ 4.96, 4.96, 7.04, 7.04 ], "texture": "#p2020" },
				"south": { "uv": [ 4.96, 4.96, 7.04, 7.04 ], "texture": "#p2020" },
				"east": { "uv": [ 4.96, 4.96, 7.04, 7.04 ], "texture": "#p2020" }
			}
		},
		{
			"__comment": "Voxels-111111",
			"from": [ 4.5, 7, 7.5 ],
			"to": [ 5, 8, 8 ],
			"faces": {
				"down": { "uv": [ 4.96, 4.96, 7.04, 7.04 ], "texture": "#p2020" },
				"north": { "uv": [ 4.96, 4.96, 7.04, 7.04 ], "texture": "#p2020" },
				"south": { "uv": [ 4.96, 4.96, 7.04, 7.04 ], "texture": "#p2020" },
				"east": { "uv": [ 4.96, 4.96, 7.04, 7.04 ], "texture": "#p2020" }
			}
		},
		{
			"__comment": "Voxels-111111",
			"from": [ 4.5, 7, 8.5 ],
			"to": [ 5, 8, 9 ],
			"faces": {
				"down": { "uv": [ 4.96, 4.96, 7.04, 7.04 ], "texture": "#p2020" },
				"north": { "uv": [ 4.96, 4.96, 7.04, 7.04 ], "texture": "#p2020" },
				"south": { "uv": [ 4.96, 4.96, 7.04, 7.04 ], "texture": "#p2020" },
				"east": { "uv": [ 4.96, 4.96, 7.04, 7.04 ], "texture": "#p2020" }
			}
		},
		{
			"__comment": "Voxels-440000",
			"from": [ 4.5, 10, 7.5 ],
			"to": [ 11.5, 10.5, 8 ],
			"faces": {
				"down": { "uv": [ 8.96, 0.96, 11.04, 3.04 ], "texture": "#p2020" },
				"north": { "uv": [ 8.96, 0.96, 11.04, 3.04 ], "texture": "#p2020" },
				"south": { "uv": [ 8.96, 0.96, 11.04, 3.04 ], "texture": "#p2020" }
			}
		},
		{
			"__comment": "Voxels-440000",
			"from": [ 4.5, 10, 8.5 ],
			"to": [ 11.5, 10.5, 9 ],
			"faces": {
				"down": { "uv": [ 8.96, 0.96, 11.04, 3.04 ], "texture": "#p2020" },
				"north": { "uv": [ 8.96, 0.96, 11.04, 3.04 ], "texture": "#p2020" },
				"south": { "uv": [ 8.96, 0.96, 11.04, 3.04 ], "texture": "#p2020" }
			}
		},
		{
			"__comment": "Voxels-000011",
			"from": [ 5, 7, 8 ],
			"to": [ 5.5, 7.5, 8.5 ],
			"faces": {
				"down": { "uv": [ 8.96, 4.96, 11.04, 7.04 ], "texture": "#p2020" },
				"north": { "uv": [ 8.96, 4.96, 11.04, 7.04 ], "texture": "#p2020" },
				"south": { "uv": [ 8.96, 4.96, 11.04, 7.04 ], "texture": "#p2020" },
				"east": { "uv": [ 8.96, 4.96, 11.04, 7.04 ], "texture": "#p2020" }
			}
		},
		{
			"__comment": "Voxels-440000",
			"from": [ 5, 7.5, 7.5 ],
			"to": [ 5.5, 8, 8 ],
			"faces": {
				"down": { "uv": [ 8.96, 0.96, 11.04, 3.04 ], "texture": "#p2020" },
				"north": { "uv": [ 8.96, 0.96, 11.04, 3.04 ], "texture": "#p2020" },
				"east": { "uv": [ 8.96, 0.96, 11.04, 3.04 ], "texture": "#p2020" }
			}
		},
		{
			"__comment": "Voxels-440000",
			"from": [ 5, 7.5, 8.5 ],
			"to": [ 5.5, 8, 9 ],
			"faces": {
				"down": { "uv": [ 8.96, 0.96, 11.04, 3.04 ], "texture": "#p2020" },
				"south": { "uv": [ 8.96, 0.96, 11.04, 3.04 ], "texture": "#p2020" },
				"east": { "uv": [ 8.96, 0.96, 11.04, 3.04 ], "texture": "#p2020" }
			}
		},
		{
			"__comment": "Voxels-000011",
			"from": [ 5, 8, 8.5 ],
			"to": [ 5.5, 9.5, 9 ],
			"faces": {
				"north": { "uv": [ 8.96, 4.96, 11.04, 7.04 ], "texture": "#p2020" },
				"south": { "uv": [ 8.96, 4.96, 11.04, 7.04 ], "texture": "#p2020" },
				"west": { "uv": [ 8.96, 4.96, 11.04, 7.04 ], "texture": "#p2020" },
				"east": { "uv": [ 8.96, 4.96, 11.04, 7.04 ], "texture": "#p2020" }
			}
		},
		{
			"__comment": "Voxels-111111",
			"from": [ 5, 9, 7.5 ],
			"to": [ 5.5, 9.5, 8 ],
			"faces": {
				"north": { "uv": [ 4.96, 4.96, 7.04, 7.04 ], "texture": "#p2020" },
				"east": { "uv": [ 4.96, 4.96, 7.04, 7.04 ], "texture": "#p2020" }
			}
		},
		{
			"__comment": "Voxels-555555",
			"from": [ 5, 11, 7.5 ],
			"to": [ 7, 11.5, 8 ],
			"faces": {
				"up": { "uv": [ 12.96, 0.96, 15.04, 3.04 ], "texture": "#p2020" },
				"north": { "uv": [ 12.96, 0.96, 15.04, 3.04 ], "texture": "#p2020" }
			}
		},
		{
			"__comment": "Voxels-555555",
			"from": [ 5, 11, 8.5 ],
			"to": [ 7, 11.5, 9 ],
			"faces": {
				"up": { "uv": [ 12.96, 0.96, 15.04, 3.04 ], "texture": "#p2020" },
				"south": { "uv": [ 12.96, 0.96, 15.04, 3.04 ], "texture": "#p2020" }
			}
		},
		{
			"__comment": "Voxels-555555",
			"from": [ 5, 11.5, 8 ],
			"to": [ 7, 12, 8.5 ],
			"faces": {
				"up": { "uv": [ 12.96, 0.96, 15.04, 3.04 ], "texture": "#p2020" },
				"north": { "uv": [ 12.96, 0.96, 15.04, 3.04 ], "texture": "#p2020" },
				"south": { "uv": [ 12.96, 0.96, 15.04, 3.04 ], "texture": "#p2020" }
			}
		},
		{
			"__comment": "Voxels-222222",
			"from": [ 5.5, 7.5, 8 ],
			"to": [ 7.5, 8, 8.5 ],
			"faces": {
				"down": { "uv": [ 0.96, 8.96, 3.04, 11.04 ], "texture": "#p2020" },
				"up": { "uv": [ 0.96, 8.96, 3.04, 11.04 ], "texture": "#p2020" },
				"north": { "uv": [ 0.96, 8.96, 3.04, 11.04 ], "texture": "#p2020" },
				"south": { "uv": [ 0.96, 8.96, 3.04, 11.04 ], "texture": "#p2020" }
			}
		},
		{
			"__comment": "Voxels-440000",
			"from": [ 5.5, 8, 8 ],
			"to": [ 6, 9.5, 8.5 ],
			"faces": {
				"north": { "uv": [ 8.96, 0.96, 11.04, 3.04 ], "texture": "#p2020" },
				"south": { "uv": [ 8.96, 0.96, 11.04, 3.04 ], "texture": "#p2020" },
				"west": { "uv": [ 8.96, 0.96, 11.04, 3.04 ], "texture": "#p2020" },
				"east": { "uv": [ 8.96, 0.96, 11.04, 3.04 ], "texture": "#p2020" }
			}
		},
		{
			"__comment": "Voxels-880000",
			"from": [ 6, 9.5, 8 ],
			"to": [ 6.5, 10, 8.5 ],
			"faces": {
				"down": { "uv": [ 12.96, 8.96, 15.04, 11.04 ], "texture": "#p2020" }
			}
		},
		{
			"__comment": "Voxels-555555",
			"from": [ 6.5, 8.5, 8 ],
			"to": [ 7, 9.5, 8.5 ],
			"faces": {
				"down": { "uv": [ 12.96, 0.96, 15.04, 3.04 ], "texture": "#p2020" },
				"north": { "uv": [ 12.96, 0.96, 15.04, 3.04 ], "texture": "#p2020" },
				"south": { "uv": [ 12.96, 0.96, 15.04, 3.04 ], "texture": "#p2020" },
				"west": { "uv": [ 12.96, 0.96, 15.04, 3.04 ], "texture": "#p2020" },
				"east": { "uv": [ 12.96, 0.96, 15.04, 3.04 ], "texture": "#p2020" }
			}
		},
		{
			"__comment": "Voxels-222222",
			"from": [ 6.5, 9.5, 7.5 ],
			"to": [ 7.5, 10, 8 ],
			"faces": {
				"down": { "uv": [ 0.96, 8.96, 3.04, 11.04 ], "texture": "#p2020" },
				"north": { "uv": [ 0.96, 8.96, 3.04, 11.04 ], "texture": "#p2020" },
				"south": { "uv": [ 0.96, 8.96, 3.04, 11.04 ], "texture": "#p2020" }
			}
		},
		{
			"__comment": "Voxels-222222",
			"from": [ 6.5, 9.5, 8.5 ],
			"to": [ 7.5, 10, 9 ],
			"faces": {
				"down": { "uv": [ 0.96, 8.96, 3.04, 11.04 ], "texture": "#p2020" },
				"north": { "uv": [ 0.96, 8.96, 3.04, 11.04 ], "texture": "#p2020" },
				"south": { "uv": [ 0.96, 8.96, 3.04, 11.04 ], "texture": "#p2020" }
			}
		},
		{
			"__comment": "Voxels-000011",
			"from": [ 7, 9.5, 8 ],
			"to": [ 8.5, 10, 8.5 ],
			"faces": {
				"down": { "uv": [ 8.96, 4.96, 11.04, 7.04 ], "texture": "#p2020" },
				"north": { "uv": [ 8.96, 4.96, 11.04, 7.04 ], "texture": "#p2020" },
				"south": { "uv": [ 8.96, 4.96, 11.04, 7.04 ], "texture": "#p2020" },
				"east": { "uv": [ 8.96, 4.96, 11.04, 7.04 ], "texture": "#p2020" }
			}
		},
		{
			"__comment": "Voxels-000011",
			"from": [ 7, 11, 7.5 ],
			"to": [ 8.5, 11.5, 8 ],
			"faces": {
				"up": { "uv": [ 8.96, 4.96, 11.04, 7.04 ], "texture": "#p2020" },
				"north": { "uv": [ 8.96, 4.96, 11.04, 7.04 ], "texture": "#p2020" }
			}
		},
		{
			"__comment": "Voxels-111111",
			"from": [ 7, 11, 8.5 ],
			"to": [ 8.5, 11.5, 9 ],
			"faces": {
				"up": { "uv": [ 4.96, 4.96, 7.04, 7.04 ], "texture": "#p2020" },
				"south": { "uv": [ 4.96, 4.96, 7.04, 7.04 ], "texture": "#p2020" }
			}
		},
		{
			"__comment": "Voxels-111111",
			"from": [ 7, 11.5, 8 ],
			"to": [ 10, 12, 8.5 ],
			"faces": {
				"up": { "uv": [ 4.96, 4.96, 7.04, 7.04 ], "texture": "#p2020" },
				"north": { "uv": [ 4.96, 4.96, 7.04, 7.04 ], "texture": "#p2020" },
				"south": { "uv": [ 4.96, 4.96, 7.04, 7.04 ], "texture": "#p2020" }
			}
		},
		{
			"__comment": "Voxels-000011",
			"from": [ 7.5, 7.5, 8 ],
			"to": [ 8, 8, 8.5 ],
			"faces": {
				"down": { "uv": [ 8.96, 4.96, 11.04, 7.04 ], "texture": "#p2020" },
				"up": { "uv": [ 8.96, 4.96, 11.04, 7.04 ], "texture": "#p2020" },
				"north": { "uv": [ 8.96, 4.96, 11.04, 7.04 ], "texture": "#p2020" },
				"south": { "uv": [ 8.96, 4.96, 11.04, 7.04 ], "texture": "#p2020" },
				"east": { "uv": [ 8.96, 4.96, 11.04, 7.04 ], "texture": "#p2020" }
			}
		},
		{
			"__comment": "Voxels-440000",
			"from": [ 7.5, 9.5, 7.5 ],
			"to": [ 8, 10, 8 ],
			"faces": {
				"down": { "uv": [ 8.96, 0.96, 11.04, 3.04 ], "texture": "#p2020" },
				"north": { "uv": [ 8.96, 0.96, 11.04, 3.04 ], "texture": "#p2020" }
			}
		},
		{
			"__comment": "Voxels-440000",
			"from": [ 7.5, 9.5, 8.5 ],
			"to": [ 8, 10, 9 ],
			"faces": {
				"down": { "uv": [ 8.96, 0.96, 11.04, 3.04 ], "texture": "#p2020" },
				"south": { "uv": [ 8.96, 0.96, 11.04, 3.04 ], "texture": "#p2020" }
			}
		},
		{
			"__comment": "Voxels-000011",
			"from": [ 8, 8, 8 ],
			"to": [ 8.5, 9.5, 8.5 ],
			"faces": {
				"down": { "uv": [ 8.96, 4.96, 11.04, 7.04 ], "texture": "#p2020" },
				"north": { "uv": [ 8.96, 4.96, 11.04, 7.04 ], "texture": "#p2020" },
				"south": { "uv": [ 8.96, 4.96, 11.04, 7.04 ], "texture": "#p2020" },
				"west": { "uv": [ 8.96, 4.96, 11.04, 7.04 ], "texture": "#p2020" },
				"east": { "uv": [ 8.96, 4.96, 11.04, 7.04 ], "texture": "#p2020" }
			}
		},
		{
			"__comment": "Voxels-000011",
			"from": [ 8, 9.5, 7.5 ],
			"to": [ 10, 10, 8 ],
			"faces": {
				"down": { "uv": [ 8.96, 4.96, 11.04, 7.04 ], "texture": "#p2020" },
				"north": { "uv": [ 8.96, 4.96, 11.04, 7.04 ], "texture": "#p2020" },
				"south": { "uv": [ 8.96, 4.96, 11.04, 7.04 ], "texture": "#p2020" }
			}
		},
		{
			"__comment": "Voxels-000011",
			"from": [ 8, 9.5, 8.5 ],
			"to": [ 10, 10, 9 ],
			"faces": {
				"down": { "uv": [ 8.96, 4.96, 11.04, 7.04 ], "texture": "#p2020" },
				"north": { "uv": [ 8.96, 4.96, 11.04, 7.04 ], "texture": "#p2020" },
				"south": { "uv": [ 8.96, 4.96, 11.04, 7.04 ], "texture": "#p2020" }
			}
		},
		{
			"__comment": "Voxels-000011",
			"from": [ 8.5, 10, 8 ],
			"to": [ 13, 10.5, 8.5 ],
			"faces": {
				"down": { "uv": [ 8.96, 4.96, 11.04, 7.04 ], "texture": "#p2020" },
				"north": { "uv": [ 8.96, 4.96, 11.04, 7.04 ], "texture": "#p2020" },
				"south": { "uv": [ 8.96, 4.96, 11.04, 7.04 ], "texture": "#p2020" }
			}
		},
		{
			"__comment": "Voxels-440000",
			"from": [ 8.5, 11, 7.5 ],
			"to": [ 9.5, 11.5, 8 ],
			"faces": {
				"up": { "uv": [ 8.96, 0.96, 11.04, 3.04 ], "texture": "#p2020" },
				"north": { "uv": [ 8.96, 0.96, 11.04, 3.04 ], "texture": "#p2020" }
			}
		},
		{
			"__comment": "Voxels-440000",
			"from": [ 8.5, 11, 8.5 ],
			"to": [ 9.5, 11.5, 9 ],
			"faces": {
				"up": { "uv": [ 8.96, 0.96, 11.04, 3.04 ], "texture": "#p2020" },
				"south": { "uv": [ 8.96, 0.96, 11.04, 3.04 ], "texture": "#p2020" }
			}
		},
		{
			"__comment": "Voxels-111111",
			"from": [ 9.5, 11, 7.5 ],
			"to": [ 10.5, 11.5, 8 ],
			"faces": {
				"up": { "uv": [ 4.96, 4.96, 7.04, 7.04 ], "texture": "#p2020" },
				"north": { "uv": [ 4.96, 4.96, 7.04, 7.04 ], "texture": "#p2020" }
			}
		},
		{
			"__comment": "Voxels-111111",
			"from": [ 9.5, 11, 8.5 ],
			"to": [ 10.5, 11.5, 9 ],
			"faces": {
				"up": { "uv": [ 4.96, 4.96, 7.04, 7.04 ], "texture": "#p2020" },
				"south": { "uv": [ 4.96, 4.96, 7.04, 7.04 ], "texture": "#p2020" }
			}
		},
		{
			"__comment": "Voxels-440000",
			"from": [ 10, 9.5, 7.5 ],
			"to": [ 13.5, 10, 8 ],
			"faces": {
				"down": { "uv": [ 8.96, 0.96, 11.04, 3.04 ], "texture": "#p2020" },
				"up": { "uv": [ 8.96, 0.96, 11.04, 3.04 ], "texture": "#p2020" },
				"north": { "uv": [ 8.96, 0.96, 11.04, 3.04 ], "texture": "#p2020" },
				"south": { "uv": [ 8.96, 0.96, 11.04, 3.04 ], "texture": "#p2020" },
				"east": { "uv": [ 8.96, 0.96, 11.04, 3.04 ], "texture": "#p2020" }
			}
		},
		{
			"__comment": "Voxels-440000",
			"from": [ 10, 9.5, 8.5 ],
			"to": [ 13.5, 10, 9 ],
			"faces": {
				"down": { "uv": [ 8.96, 0.96, 11.04, 3.04 ], "texture": "#p2020" },
				"up": { "uv": [ 8.96, 0.96, 11.04, 3.04 ], "texture": "#p2020" },
				"north": { "uv": [ 8.96, 0.96, 11.04, 3.04 ], "texture": "#p2020" },
				"south": { "uv": [ 8.96, 0.96, 11.04, 3.04 ], "texture": "#p2020" },
				"east": { "uv": [ 8.96, 0.96, 11.04, 3.04 ], "texture": "#p2020" }
			}
		},
		{
			"__comment": "Voxels-220000",
			"from": [ 10, 11.5, 8 ],
			"to": [ 10.5, 12, 8.5 ],
			"faces": {
				"up": { "uv": [ 4.96, 0.96, 7.04, 3.04 ], "texture": "#p2020" },
				"north": { "uv": [ 4.96, 0.96, 7.04, 3.04 ], "texture": "#p2020" },
				"south": { "uv": [ 4.96, 0.96, 7.04, 3.04 ], "texture": "#p2020" }
			}
		},
		{
			"__comment": "Voxels-220000",
			"from": [ 10.5, 11, 7.5 ],
			"to": [ 11, 11.5, 8 ],
			"faces": {
				"up": { "uv": [ 4.96, 0.96, 7.04, 3.04 ], "texture": "#p2020" },
				"north": { "uv": [ 4.96, 0.96, 7.04, 3.04 ], "texture": "#p2020" }
			}
		},
		{
			"__comment": "Voxels-220000",
			"from": [ 10.5, 11, 8.5 ],
			"to": [ 11, 11.5, 9 ],
			"faces": {
				"up": { "uv": [ 4.96, 0.96, 7.04, 3.04 ], "texture": "#p2020" },
				"south": { "uv": [ 4.96, 0.96, 7.04, 3.04 ], "texture": "#p2020" }
			}
		},
		{
			"__comment": "Voxels-440000",
			"from": [ 10.5, 11.5, 8 ],
			"to": [ 14, 12, 8.5 ],
			"faces": {
				"down": { "uv": [ 8.96, 0.96, 11.04, 3.04 ], "texture": "#p2020" },
				"up": { "uv": [ 8.96, 0.96, 11.04, 3.04 ], "texture": "#p2020" },
				"north": { "uv": [ 8.96, 0.96, 11.04, 3.04 ], "texture": "#p2020" },
				"south": { "uv": [ 8.96, 0.96, 11.04, 3.04 ], "texture": "#p2020" },
				"east": { "uv": [ 8.96, 0.96, 11.04, 3.04 ], "texture": "#p2020" }
			}
		},
		{
			"__comment": "Voxels-440000",
			"from": [ 11, 11, 7.5 ],
			"to": [ 12.5, 11.5, 8 ],
			"faces": {
				"down": { "uv": [ 8.96, 0.96, 11.04, 3.04 ], "texture": "#p2020" },
				"up": { "uv": [ 8.96, 0.96, 11.04, 3.04 ], "texture": "#p2020" },
				"north": { "uv": [ 8.96, 0.96, 11.04, 3.04 ], "texture": "#p2020" }
			}
		},
		{
			"__comment": "Voxels-440000",
			"from": [ 11, 11, 8.5 ],
			"to": [ 12.5, 11.5, 9 ],
			"faces": {
				"down": { "uv": [ 8.96, 0.96, 11.04, 3.04 ], "texture": "#p2020" },
				"up": { "uv": [ 8.96, 0.96, 11.04, 3.04 ], "texture": "#p2020" },
				"south": { "uv": [ 8.96, 0.96, 11.04, 3.04 ], "texture": "#p2020" }
			}
		},
		{
			"__comment": "Voxels-555555",
			"from": [ 11.5, 10, 7.5 ],
			"to": [ 12, 10.5, 8 ],
			"faces": {
				"north": { "uv": [ 12.96, 0.96, 15.04, 3.04 ], "texture": "#p2020" }
			}
		},
		{
			"__comment": "Voxels-555555",
			"from": [ 11.5, 10, 8.5 ],
			"to": [ 12, 10.5, 9 ],
			"faces": {
				"south": { "uv": [ 12.96, 0.96, 15.04, 3.04 ], "texture": "#p2020" }
			}
		},
		{
			"__comment": "Voxels-550000",
			"from": [ 11.5, 10.5, 7.5 ],
			"to": [ 12, 11, 8 ],
			"faces": {
				"north": { "uv": [ 0.96, 4.96, 3.04, 7.04 ], "texture": "#p2020" }
			}
		},
		{
			"__comment": "Voxels-440000",
			"from": [ 11.5, 10.5, 8.5 ],
			"to": [ 12, 11, 9 ],
			"faces": {
				"south": { "uv": [ 8.96, 0.96, 11.04, 3.04 ], "texture": "#p2020" }
			}
		},
		{
			"__comment": "Voxels-440000",
			"from": [ 12, 10, 7.5 ],
			"to": [ 13.5, 10.5, 8 ],
			"faces": {
				"up": { "uv": [ 8.96, 0.96, 11.04, 3.04 ], "texture": "#p2020" },
				"north": { "uv": [ 8.96, 0.96, 11.04, 3.04 ], "texture": "#p2020" },
				"south": { "uv": [ 8.96, 0.96, 11.04, 3.04 ], "texture": "#p2020" }
			}
		},
		{
			"__comment": "Voxels-440000",
			"from": [ 12, 10, 8.5 ],
			"to": [ 13.5, 10.5, 9 ],
			"faces": {
				"up": { "uv": [ 8.96, 0.96, 11.04, 3.04 ], "texture": "#p2020" },
				"north": { "uv": [ 8.96, 0.96, 11.04, 3.04 ], "texture": "#p2020" },
				"south": { "uv": [ 8.96, 0.96, 11.04, 3.04 ], "texture": "#p2020" }
			}
		},
		{
			"__comment": "Voxels-555555",
			"from": [ 12, 10.5, 7.5 ],
			"to": [ 12.5, 11, 8 ],
			"faces": {
				"north": { "uv": [ 12.96, 0.96, 15.04, 3.04 ], "texture": "#p2020" }
			}
		},
		{
			"__comment": "Voxels-555555",
			"from": [ 12, 10.5, 8.5 ],
			"to": [ 12.5, 11, 9 ],
			"faces": {
				"south": { "uv": [ 12.96, 0.96, 15.04, 3.04 ], "texture": "#p2020" }
			}
		},
		{
			"__comment": "Voxels-440000",
			"from": [ 12.5, 10.5, 7.5 ],
			"to": [ 13.5, 11, 8 ],
			"faces": {
				"up": { "uv": [ 8.96, 0.96, 11.04, 3.04 ], "texture": "#p2020" },
				"north": { "uv": [ 8.96, 0.96, 11.04, 3.04 ], "texture": "#p2020" },
				"south": { "uv": [ 8.96, 0.96, 11.04, 3.04 ], "texture": "#p2020" }
			}
		},
		{
			"__comment": "Voxels-440000",
			"from": [ 12.5, 10.5, 8.5 ],
			"to": [ 13.5, 11, 9 ],
			"faces": {
				"up": { "uv": [ 8.96, 0.96, 11.04, 3.04 ], "texture": "#p2020" },
				"north": { "uv": [ 8.96, 0.96, 11.04, 3.04 ], "texture": "#p2020" },
				"south": { "uv": [ 8.96, 0.96, 11.04, 3.04 ], "texture": "#p2020" }
			}
		},
		{
			"__comment": "Voxels-555555",
			"from": [ 12.5, 11, 7.5 ],
			"to": [ 13, 11.5, 8 ],
			"faces": {
				"up": { "uv": [ 12.96, 0.96, 15.04, 3.04 ], "texture": "#p2020" },
				"north": { "uv": [ 12.96, 0.96, 15.04, 3.04 ], "texture": "#p2020" }
			}
		},
		{
			"__comment": "Voxels-555555",
			"from": [ 12.5, 11, 8.5 ],
			"to": [ 13, 11.5, 9 ],
			"faces": {
				"up": { "uv": [ 12.96, 0.96, 15.04, 3.04 ], "texture": "#p2020" },
				"south": { "uv": [ 12.96, 0.96, 15.04, 3.04 ], "texture": "#p2020" }
			}
		},
		{
			"__comment": "Voxels-111111",
			"from": [ 13, 10, 8 ],
			"to": [ 13.5, 11.5, 8.5 ],
			"faces": {
				"down": { "uv": [ 4.96, 4.96, 7.04, 7.04 ], "texture": "#p2020" },
				"north": { "uv": [ 4.96, 4.96, 7.04, 7.04 ], "texture": "#p2020" },
				"south": { "uv": [ 4.96, 4.96, 7.04, 7.04 ], "texture": "#p2020" },
				"west": { "uv": [ 4.96, 4.96, 7.04, 7.04 ], "texture": "#p2020" },
				"east": { "uv": [ 4.96, 4.96, 7.04, 7.04 ], "texture": "#p2020" }
			}
		},
		{
			"__comment": "Voxels-440000",
			"from": [ 13, 11, 7.5 ],
			"to": [ 13.5, 11.5, 8 ],
			"faces": {
				"up": { "uv": [ 8.96, 0.96, 11.04, 3.04 ], "texture": "#p2020" },
				"north": { "uv": [ 8.96, 0.96, 11.04, 3.04 ], "texture": "#p2020" }
			}
		},
		{
			"__comment": "Voxels-440000",
			"from": [ 13, 11, 8.5 ],
			"to": [ 13.5, 11.5, 9 ],
			"faces": {
				"up": { "uv": [ 8.96, 0.96, 11.04, 3.04 ], "texture": "#p2020" },
				"south": { "uv": [ 8.96, 0.96, 11.04, 3.04 ], "texture": "#p2020" }
			}
		},
		{
			"__comment": "Voxels-440000",
			"from": [ 13.5, 9.5, 8 ],
			"to": [ 14, 10, 8.5 ],
			"faces": {
				"down": { "uv": [ 8.96, 0.96, 11.04, 3.04 ], "texture": "#p2020" },
				"up": { "uv": [ 8.96, 0.96, 11.04, 3.04 ], "texture": "#p2020" },
				"north": { "uv": [ 8.96, 0.96, 11.04, 3.04 ], "texture": "#p2020" },
				"south": { "uv": [ 8.96, 0.96, 11.04, 3.04 ], "texture": "#p2020" },
				"west": { "uv": [ 8.96, 0.96, 11.04, 3.04 ], "texture": "#p2020" },
				"east": { "uv": [ 8.96, 0.96, 11.04, 3.04 ], "texture": "#p2020" }
			}
		},
		{
			"__comment": "Voxels-220000",
			"from": [ 13.5, 10, 7.5 ],
			"to": [ 14, 11.5, 8 ],
			"faces": {
				"down": { "uv": [ 4.96, 0.96, 7.04, 3.04 ], "texture": "#p2020" },
				"up": { "uv": [ 4.96, 0.96, 7.04, 3.04 ], "texture": "#p2020" },
				"north": { "uv": [ 4.96, 0.96, 7.04, 3.04 ], "texture": "#p2020" },
				"south": { "uv": [ 4.96, 0.96, 7.04, 3.04 ], "texture": "#p2020" },
				"west": { "uv": [ 4.96, 0.96, 7.04, 3.04 ], "texture": "#p2020" },
				"east": { "uv": [ 4.96, 0.96, 7.04, 3.04 ], "texture": "#p2020" }
			}
		},
		{
			"__comment": "Voxels-220000",
			"from": [ 13.5, 10, 8.5 ],
			"to": [ 14, 11.5, 9 ],
			"faces": {
				"down": { "uv": [ 4.96, 0.96, 7.04, 3.04 ], "texture": "#p2020" },
				"up": { "uv": [ 4.96, 0.96, 7.04, 3.04 ], "texture": "#p2020" },
				"north": { "uv": [ 4.96, 0.96, 7.04, 3.04 ], "texture": "#p2020" },
				"south": { "uv": [ 4.96, 0.96, 7.04, 3.04 ], "texture": "#p2020" },
				"west": { "uv": [ 4.96, 0.96, 7.04, 3.04 ], "texture": "#p2020" },
				"east": { "uv": [ 4.96, 0.96, 7.04, 3.04 ], "texture": "#p2020" }
			}
		}
	],
	"display": {
		"thirdperson_righthand": {
			"rotation":  [ 0, 90, 5 ],
			"translation":  [ 0, -0.5, -1 ],
			"scale":  [ 0.7, 0.7, 0.7 ]
		},
		"thirdperson_lefthand": {
			"rotation":  [ 0, -90, -5 ],
			"translation":  [ 0, -0.5, -1 ],
			"scale":  [ 0.7, 0.7, 0.7 ]
		},
		"firstperson_righthand": {
			"rotation":  [ 0, 90, 5 ],
			"translation":  [ 0, 1, -1.5 ],
			"scale":  [ 0.55, 0.75, 0.75 ]
		},
		"firstperson_lefthand": {
			"rotation":  [ 0, -90, -5 ],
			"translation":  [ 0, 1, -1.5 ],
			"scale":  [ 0.55, 0.75, 0.75 ]
		},
		"head": {
			"rotation":  [ 0, 180, 0 ],
			"translation":  [ 0, 10, 0 ],
			"scale":  [ 0.7, 0.7, 0.7 ]
		},
		"ground": {
			"translation":  [ 0, 3, 0 ],
			"scale":  [ 0.7, 0.7, 0.7 ]
		},
		"fixed": {
			"rotation":  [ 0, 180, 0 ]
		}
	}
}